tomato/__init__.py
tomato/gorjeh_math.py
gorjeh_tomato-0.1.1.dist-info/METADATA
gorjeh_tomato-0.1.1.dist-info/WHEEL
gorjeh_tomato-0.1.1.dist-info/top_level.txt
gorjeh_tomato-0.1.1.dist-info/RECORD
