Metadata-Version: 2.1
Name: gorjeh-tomato
Version: 0.1.1
Summary: A fast Python library for calculating circle areas, named Gorjeh (Tomato).
Home-page: https://github.com/YourUsername/tomato
Author: Your Name
Author-email: your.email@example.com
Classifier: Programming Language :: Python :: 3
Classifier: License :: OSI Approved :: MIT License
Classifier: Operating System :: OS Independent
Requires-Python: >=3.6
Requires-Dist: math
